falocalrepo_server/__init__.py
falocalrepo_server/__main__.py
falocalrepo_server/__version__.py
falocalrepo_server/database.py
falocalrepo_server/functions.py
falocalrepo_server/server.py
falocalrepo_server/static/favicon.ico
falocalrepo_server/static/logo.png
falocalrepo_server/static/styles/bbcode.css
falocalrepo_server/static/styles/bootstrap.min.css
falocalrepo_server/static/styles/bootstrap.min.css.map
falocalrepo_server/static/styles/icons.css
falocalrepo_server/static/styles/sprite_smilies.png
falocalrepo_server/static/styles/style.css
falocalrepo_server/static/touch-icon.png
falocalrepo_server/templates/base.j2
falocalrepo_server/templates/components/cards.j2
falocalrepo_server/templates/components/comments.j2
falocalrepo_server/templates/components/icons.j2
falocalrepo_server/templates/components/navbar.j2
falocalrepo_server/templates/components/pagination.j2
falocalrepo_server/templates/components/tables.j2
falocalrepo_server/templates/components/tags.j2
falocalrepo_server/templates/pages/error.j2
falocalrepo_server/templates/pages/home.j2
falocalrepo_server/templates/pages/journal.j2
falocalrepo_server/templates/pages/journal_edit.j2
falocalrepo_server/templates/pages/search.j2
falocalrepo_server/templates/pages/settings.j2
falocalrepo_server/templates/pages/submission.j2
falocalrepo_server/templates/pages/submission_edit.j2
falocalrepo_server/templates/pages/user.j2
falocalrepo_server/templates/pages/user_edit.j2
falocalrepo_server-3.4.3.dist-info/LICENSE
falocalrepo_server-3.4.3.dist-info/METADATA
falocalrepo_server-3.4.3.dist-info/WHEEL
falocalrepo_server-3.4.3.dist-info/entry_points.txt
falocalrepo_server-3.4.3.dist-info/RECORD
