Metadata-Version: 2.1
Name: falocalrepo-server
Version: 3.4.3
Summary: Web interface for falocalrepo.
Home-page: https://github.com/FurryCoders/falocalrepo-server
License: EUPL-1.2
Author: Matteo Campinoti
Author-email: matteo.campinoti94@gmail.com
Requires-Python: >=3.10,<4.0
Classifier: Development Status :: 5 - Production/Stable
Classifier: Intended Audience :: End Users/Desktop
Classifier: License :: OSI Approved :: European Union Public Licence 1.2 (EUPL 1.2)
Classifier: Operating System :: OS Independent
Classifier: Programming Language :: Python :: 3
Classifier: Programming Language :: Python :: 3.10
Classifier: Programming Language :: Python :: 3.11
Classifier: Programming Language :: Python :: 3.12
Requires-Dist: Jinja2 (>=3.1.4,<4.0.0)
Requires-Dist: baize (>=0.23.1,<0.24.0)
Requires-Dist: bbcode (>=1.1.0,<2.0.0)
Requires-Dist: beautifulsoup4 (>=4.13.5,<5.0.0)
Requires-Dist: chardet (>=5.2.0,<6.0.0)
Requires-Dist: click (>=8.1.8,<9.0.0)
Requires-Dist: click-help-colors (>=0.9.4,<0.10.0)
Requires-Dist: falocalrepo-database (>=5.4.6,<5.5.0)
Requires-Dist: itsdangerous (>=2.2.0,<3.0.0)
Requires-Dist: lxml (>=6.0.1,<7.0.0)
Requires-Dist: orjson (>=3.11.3,<4.0.0)
Requires-Dist: pillow (>=11.3.0,<12.0.0)
Requires-Dist: python-multipart (>=0.0.20,<0.0.21)
Requires-Dist: starlette (>=0.47.3,<0.48.0)
Requires-Dist: uvicorn (>=0.35.0,<0.36.0)
Project-URL: Bug Reports, https://github.com/FurryCoders/falocalrepo-server/issues
Project-URL: Changelog, https://github.com/FurryCoders/falocalrepo-server/blob/main/CHANGELOG.md
Project-URL: Download, https://pypi.org/project/falocalrepo-server/#files
Project-URL: Repository, https://github.com/FurryCoders/falocalrepo-server
Project-URL: Source, https://github.com/FurryCoders/falocalrepo-server
